_cotton2k/__init__.py
_cotton2k/climate.py
_cotton2k/fruit.py
_cotton2k/leaf.py
_cotton2k/simulation.cp39-win_amd64.pyd
_cotton2k/soil.py
_cotton2k/state.cp39-win_amd64.pyd
_cotton2k/thermology.py
_cotton2k/utils.py
cotton2k/core/__init__.py
cotton2k/core/cotton2k.schema.json
cotton2k/core/meteorology.py
cotton2k/core/nitrogen.py
cotton2k/core/phenology.py
cotton2k/core/photo.py
cotton2k/core/root.py
cotton2k/core/simulation.py
cotton2k/core/soil_imp.csv
cotton2k/core/stem.py
cotton2k.core-0.1a1.dist-info/METADATA
cotton2k.core-0.1a1.dist-info/WHEEL
cotton2k.core-0.1a1.dist-info/top_level.txt
cotton2k.core-0.1a1.dist-info/RECORD
