Metadata-Version: 2.1
Name: cotton2k.core
Version: 0.1a1
Summary: Reimplementation for Cotton2k simulation model
Home-page: https://github.com/tcztzy/cotton2k
Author-email: Tang Ziya <tcztzy@gmail.com>
License: UNKNOWN
Project-URL: repository, https://github.com/tcztzy/cotton2k
Keywords: cotton,simulation,model
Platform: UNKNOWN
Classifier: Development Status :: 3 - Alpha
Classifier: License :: OSI Approved :: GNU General Public License v3 or later (GPLv3+)
Classifier: Intended Audience :: Science/Research
Classifier: Operating System :: Microsoft :: Windows :: Windows 10
Classifier: Operating System :: POSIX :: Linux
Classifier: Topic :: Scientific/Engineering :: Atmospheric Science
Classifier: Topic :: Scientific/Engineering :: Bio-Informatics
Classifier: Topic :: Scientific/Engineering :: Hydrology
Requires-Python: >=3.9
Requires-Dist: numpy (==1.21.2)
Requires-Dist: pint (==0.17)
Requires-Dist: scipy (==1.7.1)
